ericsearch/__init__.py
ericsearch/eric_ranker.py
ericsearch/eric_search.py
ericsearch/db/__init__.py
ericsearch/db/ericdata_dir.py
ericsearch/train/__init__.py
ericsearch/train/eric_kmeans.py
ericsearch/train/run_train.py
ericsearch/train/safetensors_dataset.py
ericsearch/utils/__init__.py
ericsearch/utils/eric_timer.py
ericsearch/utils/eric_vector.py
ericsearch/utils/get_device.py
ericsearch/utils/get_logger.py
ericsearch/utils/load_from_repo_or_path.py
ericsearch/utils/misc.py
ericsearch/utils/safetensor_writer.py
ericsearch/utils/take_dataloader.py
ericsearch/utils/types.py
ericsearch-0.0.2.dist-info/licenses/LICENSE
ericsearch-0.0.2.dist-info/METADATA
ericsearch-0.0.2.dist-info/WHEEL
ericsearch-0.0.2.dist-info/top_level.txt
ericsearch-0.0.2.dist-info/RECORD
