Metadata-Version: 2.4
Name: ericsearch
Version: 0.0.2
Summary: A local vector search engine built for speed and scalability
License: Apache 2.0
Project-URL: Repository, https://github.com/EricFillion/ericsearch
Keywords: search,vectors,embeddings,vector-search,vector-database,similarity
Classifier: Intended Audience :: Developers
Classifier: Intended Audience :: Science/Research
Classifier: License :: OSI Approved :: Apache Software License
Classifier: Programming Language :: Python :: 3
Classifier: Programming Language :: Python :: 3.10
Classifier: Programming Language :: Python :: 3.11
Classifier: Programming Language :: Python :: 3.12
Classifier: Programming Language :: Python :: 3.13
Classifier: Topic :: Scientific/Engineering :: Artificial Intelligence
License-File: LICENSE
Requires-Dist: torch>=2.2
Requires-Dist: tqdm>=4.66.3
Requires-Dist: transformers<5.0.0,>=4.57.3
Requires-Dist: huggingface-hub<1.0,>=0.34.0
Requires-Dist: sentencepiece
Requires-Dist: protobuf
Requires-Dist: tokenizers<0.23.0,>=0.22.0
Requires-Dist: sentence-transformers<6.0.0,>=5.0.0
Requires-Dist: numpy<3.0.0,>=2.0.0
Dynamic: license-file
